smithplot/__init__.py
smithplot/smithaxes.py
smithplot/smithhelper.py
pysmithplot_fork-0.2.1.dist-info/METADATA
pysmithplot_fork-0.2.1.dist-info/WHEEL
pysmithplot_fork-0.2.1.dist-info/top_level.txt
pysmithplot_fork-0.2.1.dist-info/RECORD
