Metadata-Version: 2.1
Name: pysmithplot-fork
Version: 0.2.1
Summary: An extension for Matplotlib providing a projection class to generate high quality Smith Chart plots.
Home-page: https://github.com/vMeijin/pySmithPlot
Author: Paul Staerke
Author-email: paul.staerke@gmail.com
License: BSD
Requires-Dist: matplotlib (>=1.2.0)
Requires-Dist: numpy
Requires-Dist: scipy
